{
    "mesasVotacion": [
        {
            "IMAGEN": "0",
            "NUMMESA": "001524",
            "PROCESADO": 1
        },
        {
            "IMAGEN": "0",
            "NUMMESA": "001525",
            "PROCESADO": 1
        },
        {
            "IMAGEN": "0",
            "NUMMESA": "001526",
            "PROCESADO": 1
        },
        {
            "IMAGEN": "0",
            "NUMMESA": "001527",
            "PROCESADO": 1
        },
        {
            "IMAGEN": "0",
            "NUMMESA": "001528",
            "PROCESADO": 1
        },
        {
            "IMAGEN": "0",
            "NUMMESA": "001529",
            "PROCESADO": 1
        }
    ]
}