{
    "mesasVotacion": [
        {
            "IMAGEN": "0",
            "NUMMESA": "052399",
            "PROCESADO": 1
        },
        {
            "IMAGEN": "0",
            "NUMMESA": "052400",
            "PROCESADO": 1
        },
        {
            "IMAGEN": "0",
            "NUMMESA": "052401",
            "PROCESADO": 1
        },
        {
            "IMAGEN": "0",
            "NUMMESA": "052402",
            "PROCESADO": 1
        },
        {
            "IMAGEN": "0",
            "NUMMESA": "052403",
            "PROCESADO": 1
        },
        {
            "IMAGEN": "0",
            "NUMMESA": "052404",
            "PROCESADO": 1
        },
        {
            "IMAGEN": "0",
            "NUMMESA": "052405",
            "PROCESADO": 1
        },
        {
            "IMAGEN": "0",
            "NUMMESA": "052406",
            "PROCESADO": 1
        },
        {
            "IMAGEN": "0",
            "NUMMESA": "052407",
            "PROCESADO": 1
        }
    ]
}