{
    "mesasVotacion": [
        {
            "IMAGEN": "0",
            "NUMMESA": "051510",
            "PROCESADO": 1
        },
        {
            "IMAGEN": "0",
            "NUMMESA": "051511",
            "PROCESADO": 1
        },
        {
            "IMAGEN": "0",
            "NUMMESA": "051512",
            "PROCESADO": 1
        },
        {
            "IMAGEN": "0",
            "NUMMESA": "051513",
            "PROCESADO": 1
        },
        {
            "IMAGEN": "0",
            "NUMMESA": "051514",
            "PROCESADO": 1
        },
        {
            "IMAGEN": "0",
            "NUMMESA": "051515",
            "PROCESADO": 1
        },
        {
            "IMAGEN": "0",
            "NUMMESA": "051516",
            "PROCESADO": 1
        },
        {
            "IMAGEN": "0",
            "NUMMESA": "051517",
            "PROCESADO": 1
        },
        {
            "IMAGEN": "0",
            "NUMMESA": "051518",
            "PROCESADO": 1
        },
        {
            "IMAGEN": "0",
            "NUMMESA": "051519",
            "PROCESADO": 1
        },
        {
            "IMAGEN": "0",
            "NUMMESA": "051520",
            "PROCESADO": 1
        },
        {
            "IMAGEN": "0",
            "NUMMESA": "051521",
            "PROCESADO": 1
        },
        {
            "IMAGEN": "0",
            "NUMMESA": "051522",
            "PROCESADO": 1
        },
        {
            "IMAGEN": "0",
            "NUMMESA": "051523",
            "PROCESADO": 1
        },
        {
            "IMAGEN": "0",
            "NUMMESA": "051524",
            "PROCESADO": 1
        },
        {
            "IMAGEN": "0",
            "NUMMESA": "051525",
            "PROCESADO": 1
        },
        {
            "IMAGEN": "0",
            "NUMMESA": "051526",
            "PROCESADO": 1
        },
        {
            "IMAGEN": "0",
            "NUMMESA": "051527",
            "PROCESADO": 1
        },
        {
            "IMAGEN": "0",
            "NUMMESA": "051528",
            "PROCESADO": 1
        },
        {
            "IMAGEN": "0",
            "NUMMESA": "051529",
            "PROCESADO": 1
        },
        {
            "IMAGEN": "0",
            "NUMMESA": "051530",
            "PROCESADO": 1
        },
        {
            "IMAGEN": "0",
            "NUMMESA": "051531",
            "PROCESADO": 1
        },
        {
            "IMAGEN": "0",
            "NUMMESA": "051532",
            "PROCESADO": 1
        },
        {
            "IMAGEN": "0",
            "NUMMESA": "051533",
            "PROCESADO": 1
        }
    ]
}