{
    "procesos": {
        "asistioNoVoto": "0",
        "generalCon": {
            "congresal": {
                "CCENT_COMPU": "C44057",
                "CCODI_UBIGEO": "130201",
                "CCOPIA_ACTA": "30I",
                "DEPARTAMENTO": "LAMBAYEQUE",
                "DISTRITO": "FERRE\u00d1AFE",
                "NNUME_HABILM": 300,
                "N_CANDIDATOS": 6,
                "OBSERVACION": "CONTABILIZADAS NORMALES",
                "OBSERVACION_TXT": "ACTA ELECTORAL NORMAL",
                "PROVINCIA": "FERRE\u00d1AFE",
                "TDIRE_LOCAL": "CALLE TRES MARIAS 830",
                "TNOMB_LOCAL": "IE 10059 JUAN GALO MU\u00d1OZ PALACIOS",
                "TOT_CIUDADANOS_VOTARON": 182
            },
            "resoluciones": [],
            "votos": [
                {
                    "AUTORIDAD": "FRENTE POPULAR AGRICOLA FIA DEL PERU - FREPAP",
                    "CCODI_AUTO": "00000006",
                    "CON_EMITIDOS": "1.648",
                    "CON_VALIDOS": "2.727",
                    "NLISTA": 1,
                    "TOTAL_VOTOS1": "0",
                    "TOTAL_VOTOS10": "0",
                    "TOTAL_VOTOS11": "0",
                    "TOTAL_VOTOS12": "0",
                    "TOTAL_VOTOS13": "0",
                    "TOTAL_VOTOS14": "0",
                    "TOTAL_VOTOS15": "0",
                    "TOTAL_VOTOS16": "0",
                    "TOTAL_VOTOS17": "0",
                    "TOTAL_VOTOS18": "0",
                    "TOTAL_VOTOS19": "0",
                    "TOTAL_VOTOS2": "0",
                    "TOTAL_VOTOS20": "0",
                    "TOTAL_VOTOS21": "0",
                    "TOTAL_VOTOS22": "0",
                    "TOTAL_VOTOS23": "0",
                    "TOTAL_VOTOS24": "0",
                    "TOTAL_VOTOS25": "0",
                    "TOTAL_VOTOS26": "0",
                    "TOTAL_VOTOS27": "0",
                    "TOTAL_VOTOS28": "0",
                    "TOTAL_VOTOS29": "0",
                    "TOTAL_VOTOS3": "0",
                    "TOTAL_VOTOS30": "0",
                    "TOTAL_VOTOS31": "0",
                    "TOTAL_VOTOS32": "0",
                    "TOTAL_VOTOS33": "0",
                    "TOTAL_VOTOS34": "0",
                    "TOTAL_VOTOS35": "0",
                    "TOTAL_VOTOS36": "0",
                    "TOTAL_VOTOS4": "0",
                    "TOTAL_VOTOS5": "0",
                    "TOTAL_VOTOS6": "0",
                    "TOTAL_VOTOS7": "0",
                    "TOTAL_VOTOS8": "0",
                    "TOTAL_VOTOS9": "0",
                    "congresal": "3"
                },
                {
                    "AUTORIDAD": "PARTIDO NACIONALISTA PERUANO",
                    "CCODI_AUTO": "00000012",
                    "CON_EMITIDOS": "1.099",
                    "CON_VALIDOS": "1.818",
                    "NLISTA": 2,
                    "TOTAL_VOTOS1": "1",
                    "TOTAL_VOTOS10": "0",
                    "TOTAL_VOTOS11": "0",
                    "TOTAL_VOTOS12": "0",
                    "TOTAL_VOTOS13": "0",
                    "TOTAL_VOTOS14": "0",
                    "TOTAL_VOTOS15": "0",
                    "TOTAL_VOTOS16": "0",
                    "TOTAL_VOTOS17": "0",
                    "TOTAL_VOTOS18": "0",
                    "TOTAL_VOTOS19": "0",
                    "TOTAL_VOTOS2": "0",
                    "TOTAL_VOTOS20": "0",
                    "TOTAL_VOTOS21": "0",
                    "TOTAL_VOTOS22": "0",
                    "TOTAL_VOTOS23": "0",
                    "TOTAL_VOTOS24": "0",
                    "TOTAL_VOTOS25": "0",
                    "TOTAL_VOTOS26": "0",
                    "TOTAL_VOTOS27": "0",
                    "TOTAL_VOTOS28": "0",
                    "TOTAL_VOTOS29": "0",
                    "TOTAL_VOTOS3": "0",
                    "TOTAL_VOTOS30": "0",
                    "TOTAL_VOTOS31": "0",
                    "TOTAL_VOTOS32": "0",
                    "TOTAL_VOTOS33": "0",
                    "TOTAL_VOTOS34": "0",
                    "TOTAL_VOTOS35": "0",
                    "TOTAL_VOTOS36": "0",
                    "TOTAL_VOTOS4": "0",
                    "TOTAL_VOTOS5": "0",
                    "TOTAL_VOTOS6": "0",
                    "TOTAL_VOTOS7": "0",
                    "TOTAL_VOTOS8": "0",
                    "TOTAL_VOTOS9": "0",
                    "congresal": "2"
                },
                {
                    "AUTORIDAD": " ",
                    "CCODI_AUTO": "00000000",
                    "CON_EMITIDOS": "0.000",
                    "CON_VALIDOS": "0.000",
                    "NLISTA": 3,
                    "TOTAL_VOTOS1": "0",
                    "TOTAL_VOTOS10": "0",
                    "TOTAL_VOTOS11": "0",
                    "TOTAL_VOTOS12": "0",
                    "TOTAL_VOTOS13": "0",
                    "TOTAL_VOTOS14": "0",
                    "TOTAL_VOTOS15": "0",
                    "TOTAL_VOTOS16": "0",
                    "TOTAL_VOTOS17": "0",
                    "TOTAL_VOTOS18": "0",
                    "TOTAL_VOTOS19": "0",
                    "TOTAL_VOTOS2": "0",
                    "TOTAL_VOTOS20": "0",
                    "TOTAL_VOTOS21": "0",
                    "TOTAL_VOTOS22": "0",
                    "TOTAL_VOTOS23": "0",
                    "TOTAL_VOTOS24": "0",
                    "TOTAL_VOTOS25": "0",
                    "TOTAL_VOTOS26": "0",
                    "TOTAL_VOTOS27": "0",
                    "TOTAL_VOTOS28": "0",
                    "TOTAL_VOTOS29": "0",
                    "TOTAL_VOTOS3": "0",
                    "TOTAL_VOTOS30": "0",
                    "TOTAL_VOTOS31": "0",
                    "TOTAL_VOTOS32": "0",
                    "TOTAL_VOTOS33": "0",
                    "TOTAL_VOTOS34": "0",
                    "TOTAL_VOTOS35": "0",
                    "TOTAL_VOTOS36": "0",
                    "TOTAL_VOTOS4": "0",
                    "TOTAL_VOTOS5": "0",
                    "TOTAL_VOTOS6": "0",
                    "TOTAL_VOTOS7": "0",
                    "TOTAL_VOTOS8": "0",
                    "TOTAL_VOTOS9": "0",
                    "congresal": "0"
                },
                {
                    "AUTORIDAD": "PARTIDO MORADO",
                    "CCODI_AUTO": "00000011",
                    "CON_EMITIDOS": "5.495",
                    "CON_VALIDOS": "9.091",
                    "NLISTA": 4,
                    "TOTAL_VOTOS1": "0",
                    "TOTAL_VOTOS10": "0",
                    "TOTAL_VOTOS11": "0",
                    "TOTAL_VOTOS12": "0",
                    "TOTAL_VOTOS13": "0",
                    "TOTAL_VOTOS14": "0",
                    "TOTAL_VOTOS15": "0",
                    "TOTAL_VOTOS16": "0",
                    "TOTAL_VOTOS17": "0",
                    "TOTAL_VOTOS18": "0",
                    "TOTAL_VOTOS19": "0",
                    "TOTAL_VOTOS2": "0",
                    "TOTAL_VOTOS20": "0",
                    "TOTAL_VOTOS21": "0",
                    "TOTAL_VOTOS22": "0",
                    "TOTAL_VOTOS23": "0",
                    "TOTAL_VOTOS24": "0",
                    "TOTAL_VOTOS25": "0",
                    "TOTAL_VOTOS26": "0",
                    "TOTAL_VOTOS27": "0",
                    "TOTAL_VOTOS28": "0",
                    "TOTAL_VOTOS29": "0",
                    "TOTAL_VOTOS3": "2",
                    "TOTAL_VOTOS30": "0",
                    "TOTAL_VOTOS31": "0",
                    "TOTAL_VOTOS32": "0",
                    "TOTAL_VOTOS33": "0",
                    "TOTAL_VOTOS34": "0",
                    "TOTAL_VOTOS35": "0",
                    "TOTAL_VOTOS36": "0",
                    "TOTAL_VOTOS4": "0",
                    "TOTAL_VOTOS5": "0",
                    "TOTAL_VOTOS6": "7",
                    "TOTAL_VOTOS7": "0",
                    "TOTAL_VOTOS8": "0",
                    "TOTAL_VOTOS9": "0",
                    "congresal": "10"
                },
                {
                    "AUTORIDAD": "PERU PATRIA SEGURA",
                    "CCODI_AUTO": "00000017",
                    "CON_EMITIDOS": "3.297",
                    "CON_VALIDOS": "5.455",
                    "NLISTA": 5,
                    "TOTAL_VOTOS1": "2",
                    "TOTAL_VOTOS10": "0",
                    "TOTAL_VOTOS11": "0",
                    "TOTAL_VOTOS12": "0",
                    "TOTAL_VOTOS13": "0",
                    "TOTAL_VOTOS14": "0",
                    "TOTAL_VOTOS15": "0",
                    "TOTAL_VOTOS16": "0",
                    "TOTAL_VOTOS17": "0",
                    "TOTAL_VOTOS18": "0",
                    "TOTAL_VOTOS19": "0",
                    "TOTAL_VOTOS2": "1",
                    "TOTAL_VOTOS20": "0",
                    "TOTAL_VOTOS21": "0",
                    "TOTAL_VOTOS22": "0",
                    "TOTAL_VOTOS23": "0",
                    "TOTAL_VOTOS24": "0",
                    "TOTAL_VOTOS25": "0",
                    "TOTAL_VOTOS26": "0",
                    "TOTAL_VOTOS27": "0",
                    "TOTAL_VOTOS28": "0",
                    "TOTAL_VOTOS29": "0",
                    "TOTAL_VOTOS3": "0",
                    "TOTAL_VOTOS30": "0",
                    "TOTAL_VOTOS31": "0",
                    "TOTAL_VOTOS32": "0",
                    "TOTAL_VOTOS33": "0",
                    "TOTAL_VOTOS34": "0",
                    "TOTAL_VOTOS35": "0",
                    "TOTAL_VOTOS36": "0",
                    "TOTAL_VOTOS4": "0",
                    "TOTAL_VOTOS5": "0",
                    "TOTAL_VOTOS6": "0",
                    "TOTAL_VOTOS7": "0",
                    "TOTAL_VOTOS8": "0",
                    "TOTAL_VOTOS9": "0",
                    "congresal": "6"
                },
                {
                    "AUTORIDAD": "VICTORIA NACIONAL",
                    "CCODI_AUTO": "00000022",
                    "CON_EMITIDOS": "10.989",
                    "CON_VALIDOS": "18.182",
                    "NLISTA": 6,
                    "TOTAL_VOTOS1": "7",
                    "TOTAL_VOTOS10": "0",
                    "TOTAL_VOTOS11": "0",
                    "TOTAL_VOTOS12": "0",
                    "TOTAL_VOTOS13": "0",
                    "TOTAL_VOTOS14": "0",
                    "TOTAL_VOTOS15": "0",
                    "TOTAL_VOTOS16": "0",
                    "TOTAL_VOTOS17": "0",
                    "TOTAL_VOTOS18": "0",
                    "TOTAL_VOTOS19": "0",
                    "TOTAL_VOTOS2": "5",
                    "TOTAL_VOTOS20": "0",
                    "TOTAL_VOTOS21": "0",
                    "TOTAL_VOTOS22": "0",
                    "TOTAL_VOTOS23": "0",
                    "TOTAL_VOTOS24": "0",
                    "TOTAL_VOTOS25": "0",
                    "TOTAL_VOTOS26": "0",
                    "TOTAL_VOTOS27": "0",
                    "TOTAL_VOTOS28": "0",
                    "TOTAL_VOTOS29": "0",
                    "TOTAL_VOTOS3": "4",
                    "TOTAL_VOTOS30": "0",
                    "TOTAL_VOTOS31": "0",
                    "TOTAL_VOTOS32": "0",
                    "TOTAL_VOTOS33": "0",
                    "TOTAL_VOTOS34": "0",
                    "TOTAL_VOTOS35": "0",
                    "TOTAL_VOTOS36": "0",
                    "TOTAL_VOTOS4": "5",
                    "TOTAL_VOTOS5": "0",
                    "TOTAL_VOTOS6": "1",
                    "TOTAL_VOTOS7": "0",
                    "TOTAL_VOTOS8": "0",
                    "TOTAL_VOTOS9": "0",
                    "congresal": "20"
                },
                {
                    "AUTORIDAD": "ACCION POPULAR",
                    "CCODI_AUTO": "00000001",
                    "CON_EMITIDOS": "1.099",
                    "CON_VALIDOS": "1.818",
                    "NLISTA": 7,
                    "TOTAL_VOTOS1": "1",
                    "TOTAL_VOTOS10": "0",
                    "TOTAL_VOTOS11": "0",
                    "TOTAL_VOTOS12": "0",
                    "TOTAL_VOTOS13": "0",
                    "TOTAL_VOTOS14": "0",
                    "TOTAL_VOTOS15": "0",
                    "TOTAL_VOTOS16": "0",
                    "TOTAL_VOTOS17": "0",
                    "TOTAL_VOTOS18": "0",
                    "TOTAL_VOTOS19": "0",
                    "TOTAL_VOTOS2": "1",
                    "TOTAL_VOTOS20": "0",
                    "TOTAL_VOTOS21": "0",
                    "TOTAL_VOTOS22": "0",
                    "TOTAL_VOTOS23": "0",
                    "TOTAL_VOTOS24": "0",
                    "TOTAL_VOTOS25": "0",
                    "TOTAL_VOTOS26": "0",
                    "TOTAL_VOTOS27": "0",
                    "TOTAL_VOTOS28": "0",
                    "TOTAL_VOTOS29": "0",
                    "TOTAL_VOTOS3": "0",
                    "TOTAL_VOTOS30": "0",
                    "TOTAL_VOTOS31": "0",
                    "TOTAL_VOTOS32": "0",
                    "TOTAL_VOTOS33": "0",
                    "TOTAL_VOTOS34": "0",
                    "TOTAL_VOTOS35": "0",
                    "TOTAL_VOTOS36": "0",
                    "TOTAL_VOTOS4": "0",
                    "TOTAL_VOTOS5": "0",
                    "TOTAL_VOTOS6": "0",
                    "TOTAL_VOTOS7": "0",
                    "TOTAL_VOTOS8": "0",
                    "TOTAL_VOTOS9": "0",
                    "congresal": "2"
                },
                {
                    "AUTORIDAD": "AVANZA PAIS - PARTIDO DE INTEGRACION SOCIAL",
                    "CCODI_AUTO": "00000003",
                    "CON_EMITIDOS": "1.099",
                    "CON_VALIDOS": "1.818",
                    "NLISTA": 8,
                    "TOTAL_VOTOS1": "1",
                    "TOTAL_VOTOS10": "0",
                    "TOTAL_VOTOS11": "0",
                    "TOTAL_VOTOS12": "0",
                    "TOTAL_VOTOS13": "0",
                    "TOTAL_VOTOS14": "0",
                    "TOTAL_VOTOS15": "0",
                    "TOTAL_VOTOS16": "0",
                    "TOTAL_VOTOS17": "0",
                    "TOTAL_VOTOS18": "0",
                    "TOTAL_VOTOS19": "0",
                    "TOTAL_VOTOS2": "0",
                    "TOTAL_VOTOS20": "0",
                    "TOTAL_VOTOS21": "0",
                    "TOTAL_VOTOS22": "0",
                    "TOTAL_VOTOS23": "0",
                    "TOTAL_VOTOS24": "0",
                    "TOTAL_VOTOS25": "0",
                    "TOTAL_VOTOS26": "0",
                    "TOTAL_VOTOS27": "0",
                    "TOTAL_VOTOS28": "0",
                    "TOTAL_VOTOS29": "0",
                    "TOTAL_VOTOS3": "0",
                    "TOTAL_VOTOS30": "0",
                    "TOTAL_VOTOS31": "0",
                    "TOTAL_VOTOS32": "0",
                    "TOTAL_VOTOS33": "0",
                    "TOTAL_VOTOS34": "0",
                    "TOTAL_VOTOS35": "0",
                    "TOTAL_VOTOS36": "0",
                    "TOTAL_VOTOS4": "0",
                    "TOTAL_VOTOS5": "1",
                    "TOTAL_VOTOS6": "0",
                    "TOTAL_VOTOS7": "0",
                    "TOTAL_VOTOS8": "0",
                    "TOTAL_VOTOS9": "0",
                    "congresal": "2"
                },
                {
                    "AUTORIDAD": "PODEMOS PERU",
                    "CCODI_AUTO": "00000018",
                    "CON_EMITIDOS": "4.945",
                    "CON_VALIDOS": "8.182",
                    "NLISTA": 9,
                    "TOTAL_VOTOS1": "5",
                    "TOTAL_VOTOS10": "0",
                    "TOTAL_VOTOS11": "0",
                    "TOTAL_VOTOS12": "0",
                    "TOTAL_VOTOS13": "0",
                    "TOTAL_VOTOS14": "0",
                    "TOTAL_VOTOS15": "0",
                    "TOTAL_VOTOS16": "0",
                    "TOTAL_VOTOS17": "0",
                    "TOTAL_VOTOS18": "0",
                    "TOTAL_VOTOS19": "0",
                    "TOTAL_VOTOS2": "2",
                    "TOTAL_VOTOS20": "0",
                    "TOTAL_VOTOS21": "0",
                    "TOTAL_VOTOS22": "0",
                    "TOTAL_VOTOS23": "0",
                    "TOTAL_VOTOS24": "0",
                    "TOTAL_VOTOS25": "0",
                    "TOTAL_VOTOS26": "0",
                    "TOTAL_VOTOS27": "0",
                    "TOTAL_VOTOS28": "0",
                    "TOTAL_VOTOS29": "0",
                    "TOTAL_VOTOS3": "1",
                    "TOTAL_VOTOS30": "0",
                    "TOTAL_VOTOS31": "0",
                    "TOTAL_VOTOS32": "0",
                    "TOTAL_VOTOS33": "0",
                    "TOTAL_VOTOS34": "0",
                    "TOTAL_VOTOS35": "0",
                    "TOTAL_VOTOS36": "0",
                    "TOTAL_VOTOS4": "0",
                    "TOTAL_VOTOS5": "1",
                    "TOTAL_VOTOS6": "2",
                    "TOTAL_VOTOS7": "0",
                    "TOTAL_VOTOS8": "0",
                    "TOTAL_VOTOS9": "0",
                    "congresal": "9"
                },
                {
                    "AUTORIDAD": "JUNTOS POR EL PERU",
                    "CCODI_AUTO": "00000008",
                    "CON_EMITIDOS": "0.000",
                    "CON_VALIDOS": "0.000",
                    "NLISTA": 10,
                    "TOTAL_VOTOS1": "0",
                    "TOTAL_VOTOS10": "0",
                    "TOTAL_VOTOS11": "0",
                    "TOTAL_VOTOS12": "0",
                    "TOTAL_VOTOS13": "0",
                    "TOTAL_VOTOS14": "0",
                    "TOTAL_VOTOS15": "0",
                    "TOTAL_VOTOS16": "0",
                    "TOTAL_VOTOS17": "0",
                    "TOTAL_VOTOS18": "0",
                    "TOTAL_VOTOS19": "0",
                    "TOTAL_VOTOS2": "0",
                    "TOTAL_VOTOS20": "0",
                    "TOTAL_VOTOS21": "0",
                    "TOTAL_VOTOS22": "0",
                    "TOTAL_VOTOS23": "0",
                    "TOTAL_VOTOS24": "0",
                    "TOTAL_VOTOS25": "0",
                    "TOTAL_VOTOS26": "0",
                    "TOTAL_VOTOS27": "0",
                    "TOTAL_VOTOS28": "0",
                    "TOTAL_VOTOS29": "0",
                    "TOTAL_VOTOS3": "0",
                    "TOTAL_VOTOS30": "0",
                    "TOTAL_VOTOS31": "0",
                    "TOTAL_VOTOS32": "0",
                    "TOTAL_VOTOS33": "0",
                    "TOTAL_VOTOS34": "0",
                    "TOTAL_VOTOS35": "0",
                    "TOTAL_VOTOS36": "0",
                    "TOTAL_VOTOS4": "0",
                    "TOTAL_VOTOS5": "0",
                    "TOTAL_VOTOS6": "0",
                    "TOTAL_VOTOS7": "0",
                    "TOTAL_VOTOS8": "0",
                    "TOTAL_VOTOS9": "0",
                    "congresal": "0"
                },
                {
                    "AUTORIDAD": "PARTIDO POPULAR CRISTIANO - PPC",
                    "CCODI_AUTO": "00000015",
                    "CON_EMITIDOS": "4.945",
                    "CON_VALIDOS": "8.182",
                    "NLISTA": 11,
                    "TOTAL_VOTOS1": "1",
                    "TOTAL_VOTOS10": "0",
                    "TOTAL_VOTOS11": "0",
                    "TOTAL_VOTOS12": "0",
                    "TOTAL_VOTOS13": "0",
                    "TOTAL_VOTOS14": "0",
                    "TOTAL_VOTOS15": "0",
                    "TOTAL_VOTOS16": "0",
                    "TOTAL_VOTOS17": "0",
                    "TOTAL_VOTOS18": "0",
                    "TOTAL_VOTOS19": "0",
                    "TOTAL_VOTOS2": "0",
                    "TOTAL_VOTOS20": "0",
                    "TOTAL_VOTOS21": "0",
                    "TOTAL_VOTOS22": "0",
                    "TOTAL_VOTOS23": "0",
                    "TOTAL_VOTOS24": "0",
                    "TOTAL_VOTOS25": "0",
                    "TOTAL_VOTOS26": "0",
                    "TOTAL_VOTOS27": "0",
                    "TOTAL_VOTOS28": "0",
                    "TOTAL_VOTOS29": "0",
                    "TOTAL_VOTOS3": "0",
                    "TOTAL_VOTOS30": "0",
                    "TOTAL_VOTOS31": "0",
                    "TOTAL_VOTOS32": "0",
                    "TOTAL_VOTOS33": "0",
                    "TOTAL_VOTOS34": "0",
                    "TOTAL_VOTOS35": "0",
                    "TOTAL_VOTOS36": "0",
                    "TOTAL_VOTOS4": "2",
                    "TOTAL_VOTOS5": "1",
                    "TOTAL_VOTOS6": "0",
                    "TOTAL_VOTOS7": "0",
                    "TOTAL_VOTOS8": "0",
                    "TOTAL_VOTOS9": "0",
                    "congresal": "9"
                },
                {
                    "AUTORIDAD": "FUERZA POPULAR",
                    "CCODI_AUTO": "00000007",
                    "CON_EMITIDOS": "0.000",
                    "CON_VALIDOS": "0.000",
                    "NLISTA": 12,
                    "TOTAL_VOTOS1": "0",
                    "TOTAL_VOTOS10": "0",
                    "TOTAL_VOTOS11": "0",
                    "TOTAL_VOTOS12": "0",
                    "TOTAL_VOTOS13": "0",
                    "TOTAL_VOTOS14": "0",
                    "TOTAL_VOTOS15": "0",
                    "TOTAL_VOTOS16": "0",
                    "TOTAL_VOTOS17": "0",
                    "TOTAL_VOTOS18": "0",
                    "TOTAL_VOTOS19": "0",
                    "TOTAL_VOTOS2": "0",
                    "TOTAL_VOTOS20": "0",
                    "TOTAL_VOTOS21": "0",
                    "TOTAL_VOTOS22": "0",
                    "TOTAL_VOTOS23": "0",
                    "TOTAL_VOTOS24": "0",
                    "TOTAL_VOTOS25": "0",
                    "TOTAL_VOTOS26": "0",
                    "TOTAL_VOTOS27": "0",
                    "TOTAL_VOTOS28": "0",
                    "TOTAL_VOTOS29": "0",
                    "TOTAL_VOTOS3": "0",
                    "TOTAL_VOTOS30": "0",
                    "TOTAL_VOTOS31": "0",
                    "TOTAL_VOTOS32": "0",
                    "TOTAL_VOTOS33": "0",
                    "TOTAL_VOTOS34": "0",
                    "TOTAL_VOTOS35": "0",
                    "TOTAL_VOTOS36": "0",
                    "TOTAL_VOTOS4": "0",
                    "TOTAL_VOTOS5": "0",
                    "TOTAL_VOTOS6": "0",
                    "TOTAL_VOTOS7": "0",
                    "TOTAL_VOTOS8": "0",
                    "TOTAL_VOTOS9": "0",
                    "congresal": "0"
                },
                {
                    "AUTORIDAD": "UNION POR EL PERU",
                    "CCODI_AUTO": "00000021",
                    "CON_EMITIDOS": "6.044",
                    "CON_VALIDOS": "10.000",
                    "NLISTA": 14,
                    "TOTAL_VOTOS1": "3",
                    "TOTAL_VOTOS10": "0",
                    "TOTAL_VOTOS11": "0",
                    "TOTAL_VOTOS12": "0",
                    "TOTAL_VOTOS13": "0",
                    "TOTAL_VOTOS14": "0",
                    "TOTAL_VOTOS15": "0",
                    "TOTAL_VOTOS16": "0",
                    "TOTAL_VOTOS17": "0",
                    "TOTAL_VOTOS18": "0",
                    "TOTAL_VOTOS19": "0",
                    "TOTAL_VOTOS2": "3",
                    "TOTAL_VOTOS20": "0",
                    "TOTAL_VOTOS21": "0",
                    "TOTAL_VOTOS22": "0",
                    "TOTAL_VOTOS23": "0",
                    "TOTAL_VOTOS24": "0",
                    "TOTAL_VOTOS25": "0",
                    "TOTAL_VOTOS26": "0",
                    "TOTAL_VOTOS27": "0",
                    "TOTAL_VOTOS28": "0",
                    "TOTAL_VOTOS29": "0",
                    "TOTAL_VOTOS3": "0",
                    "TOTAL_VOTOS30": "0",
                    "TOTAL_VOTOS31": "0",
                    "TOTAL_VOTOS32": "0",
                    "TOTAL_VOTOS33": "0",
                    "TOTAL_VOTOS34": "0",
                    "TOTAL_VOTOS35": "0",
                    "TOTAL_VOTOS36": "0",
                    "TOTAL_VOTOS4": "1",
                    "TOTAL_VOTOS5": "0",
                    "TOTAL_VOTOS6": "0",
                    "TOTAL_VOTOS7": "0",
                    "TOTAL_VOTOS8": "0",
                    "TOTAL_VOTOS9": "0",
                    "congresal": "11"
                },
                {
                    "AUTORIDAD": "RENOVACION POPULAR",
                    "CCODI_AUTO": "00000020",
                    "CON_EMITIDOS": "0.000",
                    "CON_VALIDOS": "0.000",
                    "NLISTA": 15,
                    "TOTAL_VOTOS1": "0",
                    "TOTAL_VOTOS10": "0",
                    "TOTAL_VOTOS11": "0",
                    "TOTAL_VOTOS12": "0",
                    "TOTAL_VOTOS13": "0",
                    "TOTAL_VOTOS14": "0",
                    "TOTAL_VOTOS15": "0",
                    "TOTAL_VOTOS16": "0",
                    "TOTAL_VOTOS17": "0",
                    "TOTAL_VOTOS18": "0",
                    "TOTAL_VOTOS19": "0",
                    "TOTAL_VOTOS2": "0",
                    "TOTAL_VOTOS20": "0",
                    "TOTAL_VOTOS21": "0",
                    "TOTAL_VOTOS22": "0",
                    "TOTAL_VOTOS23": "0",
                    "TOTAL_VOTOS24": "0",
                    "TOTAL_VOTOS25": "0",
                    "TOTAL_VOTOS26": "0",
                    "TOTAL_VOTOS27": "0",
                    "TOTAL_VOTOS28": "0",
                    "TOTAL_VOTOS29": "0",
                    "TOTAL_VOTOS3": "0",
                    "TOTAL_VOTOS30": "0",
                    "TOTAL_VOTOS31": "0",
                    "TOTAL_VOTOS32": "0",
                    "TOTAL_VOTOS33": "0",
                    "TOTAL_VOTOS34": "0",
                    "TOTAL_VOTOS35": "0",
                    "TOTAL_VOTOS36": "0",
                    "TOTAL_VOTOS4": "0",
                    "TOTAL_VOTOS5": "0",
                    "TOTAL_VOTOS6": "0",
                    "TOTAL_VOTOS7": "0",
                    "TOTAL_VOTOS8": "0",
                    "TOTAL_VOTOS9": "0",
                    "congresal": "0"
                },
                {
                    "AUTORIDAD": "RENACIMIENTO UNIDO NACIONAL",
                    "CCODI_AUTO": "00000019",
                    "CON_EMITIDOS": "0.000",
                    "CON_VALIDOS": "0.000",
                    "NLISTA": 16,
                    "TOTAL_VOTOS1": "0",
                    "TOTAL_VOTOS10": "0",
                    "TOTAL_VOTOS11": "0",
                    "TOTAL_VOTOS12": "0",
                    "TOTAL_VOTOS13": "0",
                    "TOTAL_VOTOS14": "0",
                    "TOTAL_VOTOS15": "0",
                    "TOTAL_VOTOS16": "0",
                    "TOTAL_VOTOS17": "0",
                    "TOTAL_VOTOS18": "0",
                    "TOTAL_VOTOS19": "0",
                    "TOTAL_VOTOS2": "0",
                    "TOTAL_VOTOS20": "0",
                    "TOTAL_VOTOS21": "0",
                    "TOTAL_VOTOS22": "0",
                    "TOTAL_VOTOS23": "0",
                    "TOTAL_VOTOS24": "0",
                    "TOTAL_VOTOS25": "0",
                    "TOTAL_VOTOS26": "0",
                    "TOTAL_VOTOS27": "0",
                    "TOTAL_VOTOS28": "0",
                    "TOTAL_VOTOS29": "0",
                    "TOTAL_VOTOS3": "0",
                    "TOTAL_VOTOS30": "0",
                    "TOTAL_VOTOS31": "0",
                    "TOTAL_VOTOS32": "0",
                    "TOTAL_VOTOS33": "0",
                    "TOTAL_VOTOS34": "0",
                    "TOTAL_VOTOS35": "0",
                    "TOTAL_VOTOS36": "0",
                    "TOTAL_VOTOS4": "0",
                    "TOTAL_VOTOS5": "0",
                    "TOTAL_VOTOS6": "0",
                    "TOTAL_VOTOS7": "0",
                    "TOTAL_VOTOS8": "0",
                    "TOTAL_VOTOS9": "0",
                    "congresal": "0"
                },
                {
                    "AUTORIDAD": "PARTIDO DEMOCRATICO SOMOS PERU",
                    "CCODI_AUTO": "00000010",
                    "CON_EMITIDOS": "3.846",
                    "CON_VALIDOS": "6.364",
                    "NLISTA": 17,
                    "TOTAL_VOTOS1": "3",
                    "TOTAL_VOTOS10": "0",
                    "TOTAL_VOTOS11": "0",
                    "TOTAL_VOTOS12": "0",
                    "TOTAL_VOTOS13": "0",
                    "TOTAL_VOTOS14": "0",
                    "TOTAL_VOTOS15": "0",
                    "TOTAL_VOTOS16": "0",
                    "TOTAL_VOTOS17": "0",
                    "TOTAL_VOTOS18": "0",
                    "TOTAL_VOTOS19": "0",
                    "TOTAL_VOTOS2": "2",
                    "TOTAL_VOTOS20": "0",
                    "TOTAL_VOTOS21": "0",
                    "TOTAL_VOTOS22": "0",
                    "TOTAL_VOTOS23": "0",
                    "TOTAL_VOTOS24": "0",
                    "TOTAL_VOTOS25": "0",
                    "TOTAL_VOTOS26": "0",
                    "TOTAL_VOTOS27": "0",
                    "TOTAL_VOTOS28": "0",
                    "TOTAL_VOTOS29": "0",
                    "TOTAL_VOTOS3": "1",
                    "TOTAL_VOTOS30": "0",
                    "TOTAL_VOTOS31": "0",
                    "TOTAL_VOTOS32": "0",
                    "TOTAL_VOTOS33": "0",
                    "TOTAL_VOTOS34": "0",
                    "TOTAL_VOTOS35": "0",
                    "TOTAL_VOTOS36": "0",
                    "TOTAL_VOTOS4": "1",
                    "TOTAL_VOTOS5": "0",
                    "TOTAL_VOTOS6": "0",
                    "TOTAL_VOTOS7": "0",
                    "TOTAL_VOTOS8": "0",
                    "TOTAL_VOTOS9": "0",
                    "congresal": "7"
                },
                {
                    "AUTORIDAD": "PARTIDO POLITICO NACIONAL PERU LIBRE",
                    "CCODI_AUTO": "00000014",
                    "CON_EMITIDOS": "5.495",
                    "CON_VALIDOS": "9.091",
                    "NLISTA": 18,
                    "TOTAL_VOTOS1": "3",
                    "TOTAL_VOTOS10": "0",
                    "TOTAL_VOTOS11": "0",
                    "TOTAL_VOTOS12": "0",
                    "TOTAL_VOTOS13": "0",
                    "TOTAL_VOTOS14": "0",
                    "TOTAL_VOTOS15": "0",
                    "TOTAL_VOTOS16": "0",
                    "TOTAL_VOTOS17": "0",
                    "TOTAL_VOTOS18": "0",
                    "TOTAL_VOTOS19": "0",
                    "TOTAL_VOTOS2": "0",
                    "TOTAL_VOTOS20": "0",
                    "TOTAL_VOTOS21": "0",
                    "TOTAL_VOTOS22": "0",
                    "TOTAL_VOTOS23": "0",
                    "TOTAL_VOTOS24": "0",
                    "TOTAL_VOTOS25": "0",
                    "TOTAL_VOTOS26": "0",
                    "TOTAL_VOTOS27": "0",
                    "TOTAL_VOTOS28": "0",
                    "TOTAL_VOTOS29": "0",
                    "TOTAL_VOTOS3": "2",
                    "TOTAL_VOTOS30": "0",
                    "TOTAL_VOTOS31": "0",
                    "TOTAL_VOTOS32": "0",
                    "TOTAL_VOTOS33": "0",
                    "TOTAL_VOTOS34": "0",
                    "TOTAL_VOTOS35": "0",
                    "TOTAL_VOTOS36": "0",
                    "TOTAL_VOTOS4": "0",
                    "TOTAL_VOTOS5": "0",
                    "TOTAL_VOTOS6": "0",
                    "TOTAL_VOTOS7": "0",
                    "TOTAL_VOTOS8": "0",
                    "TOTAL_VOTOS9": "0",
                    "congresal": "10"
                },
                {
                    "AUTORIDAD": "DEMOCRACIA DIRECTA",
                    "CCODI_AUTO": "00000004",
                    "CON_EMITIDOS": "10.440",
                    "CON_VALIDOS": "17.273",
                    "NLISTA": 19,
                    "TOTAL_VOTOS1": "4",
                    "TOTAL_VOTOS10": "0",
                    "TOTAL_VOTOS11": "0",
                    "TOTAL_VOTOS12": "0",
                    "TOTAL_VOTOS13": "0",
                    "TOTAL_VOTOS14": "0",
                    "TOTAL_VOTOS15": "0",
                    "TOTAL_VOTOS16": "0",
                    "TOTAL_VOTOS17": "0",
                    "TOTAL_VOTOS18": "0",
                    "TOTAL_VOTOS19": "0",
                    "TOTAL_VOTOS2": "8",
                    "TOTAL_VOTOS20": "0",
                    "TOTAL_VOTOS21": "0",
                    "TOTAL_VOTOS22": "0",
                    "TOTAL_VOTOS23": "0",
                    "TOTAL_VOTOS24": "0",
                    "TOTAL_VOTOS25": "0",
                    "TOTAL_VOTOS26": "0",
                    "TOTAL_VOTOS27": "0",
                    "TOTAL_VOTOS28": "0",
                    "TOTAL_VOTOS29": "0",
                    "TOTAL_VOTOS3": "2",
                    "TOTAL_VOTOS30": "0",
                    "TOTAL_VOTOS31": "0",
                    "TOTAL_VOTOS32": "0",
                    "TOTAL_VOTOS33": "0",
                    "TOTAL_VOTOS34": "0",
                    "TOTAL_VOTOS35": "0",
                    "TOTAL_VOTOS36": "0",
                    "TOTAL_VOTOS4": "1",
                    "TOTAL_VOTOS5": "1",
                    "TOTAL_VOTOS6": "0",
                    "TOTAL_VOTOS7": "0",
                    "TOTAL_VOTOS8": "0",
                    "TOTAL_VOTOS9": "0",
                    "congresal": "19"
                },
                {
                    "AUTORIDAD": "ALIANZA PARA EL PROGRESO",
                    "CCODI_AUTO": "00000002",
                    "CON_EMITIDOS": "0.000",
                    "CON_VALIDOS": "0.000",
                    "NLISTA": 20,
                    "TOTAL_VOTOS1": "0",
                    "TOTAL_VOTOS10": "0",
                    "TOTAL_VOTOS11": "0",
                    "TOTAL_VOTOS12": "0",
                    "TOTAL_VOTOS13": "0",
                    "TOTAL_VOTOS14": "0",
                    "TOTAL_VOTOS15": "0",
                    "TOTAL_VOTOS16": "0",
                    "TOTAL_VOTOS17": "0",
                    "TOTAL_VOTOS18": "0",
                    "TOTAL_VOTOS19": "0",
                    "TOTAL_VOTOS2": "0",
                    "TOTAL_VOTOS20": "0",
                    "TOTAL_VOTOS21": "0",
                    "TOTAL_VOTOS22": "0",
                    "TOTAL_VOTOS23": "0",
                    "TOTAL_VOTOS24": "0",
                    "TOTAL_VOTOS25": "0",
                    "TOTAL_VOTOS26": "0",
                    "TOTAL_VOTOS27": "0",
                    "TOTAL_VOTOS28": "0",
                    "TOTAL_VOTOS29": "0",
                    "TOTAL_VOTOS3": "0",
                    "TOTAL_VOTOS30": "0",
                    "TOTAL_VOTOS31": "0",
                    "TOTAL_VOTOS32": "0",
                    "TOTAL_VOTOS33": "0",
                    "TOTAL_VOTOS34": "0",
                    "TOTAL_VOTOS35": "0",
                    "TOTAL_VOTOS36": "0",
                    "TOTAL_VOTOS4": "0",
                    "TOTAL_VOTOS5": "0",
                    "TOTAL_VOTOS6": "0",
                    "TOTAL_VOTOS7": "0",
                    "TOTAL_VOTOS8": "0",
                    "TOTAL_VOTOS9": "0",
                    "congresal": "0"
                },
                {
                    "AUTORIDAD": "TOTAL VOTOS VALIDOS",
                    "CCODI_AUTO": null,
                    "CON_EMITIDOS": "60.440",
                    "CON_VALIDOS": "100.000",
                    "congresal": "110"
                },
                {
                    "AUTORIDAD": "VOTOS EN BLANCO",
                    "CCODI_AUTO": "80",
                    "CON_EMITIDOS": "14.286",
                    "CON_VALIDOS": null,
                    "congresal": "26"
                },
                {
                    "AUTORIDAD": "VOTOS NULOS",
                    "CCODI_AUTO": "80",
                    "CON_EMITIDOS": "25.275",
                    "CON_VALIDOS": null,
                    "congresal": "46"
                },
                {
                    "AUTORIDAD": "VOTOS IMPUGNADOS",
                    "CCODI_AUTO": "80",
                    "CON_EMITIDOS": "0.000",
                    "CON_VALIDOS": null,
                    "congresal": "0"
                },
                {
                    "AUTORIDAD": "TOTAL VOTOS EMITIDOS",
                    "CCODI_AUTO": null,
                    "CON_EMITIDOS": "100.000",
                    "CON_VALIDOS": "60.440",
                    "congresal": "182"
                }
            ]
        },
        "generalPar": {
            "parlamento": {
                "CCENT_COMPU": "C44057",
                "CCODI_UBIGEO": "130201",
                "CCOPIA_ACTA": "64O",
                "DEPARTAMENTO": "LAMBAYEQUE",
                "DISTRITO": "FERRE\u00d1AFE",
                "NNUME_HABILM": 300,
                "N_CANDIDATOS": 16,
                "OBSERVACION": "CONTABILIZADAS NORMALES",
                "OBSERVACION_TXT": "ACTA ELECTORAL RESUELTA",
                "PROVINCIA": "FERRE\u00d1AFE",
                "TDIRE_LOCAL": "CALLE TRES MARIAS 830",
                "TNOMB_LOCAL": "IE 10059 JUAN GALO MU\u00d1OZ PALACIOS",
                "TOT_CIUDADANOS_VOTARON": 182
            },
            "resoluciones": [
                {
                    "CCENT_COMPU": "C44057",
                    "CESTADO_RESOL": "P",
                    "CNUME_ACTA": "032368",
                    "CNUME_RESOL": "C44057000396",
                    "CNUME_RESOL_JNE": "2021035734                                        00526-2021-JEE-LAMB/JNE",
                    "CPROCED_RESOL": "JE",
                    "IMAGEN": "https://presentacioneg2021-actas-resultados-prod.s3.amazonaws.com/RE/C44057/PCP/REPCPC44057000396.PDF?X-Amz-Algorithm=AWS4-HMAC-SHA256&X-Amz-Credential=AKIAXQU6GNJSVXR2WUHM%2F20210613%2Fus-east-1%2Fs3%2Faws4_request&X-Amz-Date=20210613T181928Z&X-Amz-Expires=6000&X-Amz-SignedHeaders=host&X-Amz-Signature=9c2a48d4bd9c07b0feb7ac29028bea577c3b421b16ee1a076d6742524cabe6a7"
                }
            ],
            "votos": [
                {
                    "AUTORIDAD": "FRENTE POPULAR AGRICOLA FIA DEL PERU - FREPAP",
                    "CCODI_AUTO": "00000006",
                    "CON_EMITIDOS": "1.648",
                    "CON_VALIDOS": "4.348",
                    "NLISTA": 1,
                    "TOTAL_VOTOS1": "2",
                    "TOTAL_VOTOS10": "0",
                    "TOTAL_VOTOS11": "0",
                    "TOTAL_VOTOS12": "0",
                    "TOTAL_VOTOS13": "0",
                    "TOTAL_VOTOS14": "0",
                    "TOTAL_VOTOS15": "0",
                    "TOTAL_VOTOS16": "0",
                    "TOTAL_VOTOS2": "2",
                    "TOTAL_VOTOS3": "0",
                    "TOTAL_VOTOS4": "0",
                    "TOTAL_VOTOS5": "0",
                    "TOTAL_VOTOS6": "0",
                    "TOTAL_VOTOS7": "0",
                    "TOTAL_VOTOS8": "0",
                    "TOTAL_VOTOS9": "0",
                    "congresal": "3"
                },
                {
                    "AUTORIDAD": "PARTIDO NACIONALISTA PERUANO",
                    "CCODI_AUTO": "00000012",
                    "CON_EMITIDOS": "0.549",
                    "CON_VALIDOS": "1.449",
                    "NLISTA": 2,
                    "TOTAL_VOTOS1": "0",
                    "TOTAL_VOTOS10": "0",
                    "TOTAL_VOTOS11": "0",
                    "TOTAL_VOTOS12": "0",
                    "TOTAL_VOTOS13": "0",
                    "TOTAL_VOTOS14": "0",
                    "TOTAL_VOTOS15": "0",
                    "TOTAL_VOTOS16": "0",
                    "TOTAL_VOTOS2": "0",
                    "TOTAL_VOTOS3": "0",
                    "TOTAL_VOTOS4": "0",
                    "TOTAL_VOTOS5": "0",
                    "TOTAL_VOTOS6": "0",
                    "TOTAL_VOTOS7": "0",
                    "TOTAL_VOTOS8": "0",
                    "TOTAL_VOTOS9": "0",
                    "congresal": "1"
                },
                {
                    "AUTORIDAD": "EL FRENTE AMPLIO POR JUSTICIA, VIDA Y LIBERTAD",
                    "CCODI_AUTO": "00000005",
                    "CON_EMITIDOS": "0.549",
                    "CON_VALIDOS": "1.449",
                    "NLISTA": 3,
                    "TOTAL_VOTOS1": "1",
                    "TOTAL_VOTOS10": "0",
                    "TOTAL_VOTOS11": "0",
                    "TOTAL_VOTOS12": "0",
                    "TOTAL_VOTOS13": "0",
                    "TOTAL_VOTOS14": "0",
                    "TOTAL_VOTOS15": "0",
                    "TOTAL_VOTOS16": "0",
                    "TOTAL_VOTOS2": "0",
                    "TOTAL_VOTOS3": "1",
                    "TOTAL_VOTOS4": "0",
                    "TOTAL_VOTOS5": "0",
                    "TOTAL_VOTOS6": "0",
                    "TOTAL_VOTOS7": "0",
                    "TOTAL_VOTOS8": "0",
                    "TOTAL_VOTOS9": "0",
                    "congresal": "1"
                },
                {
                    "AUTORIDAD": "PARTIDO MORADO",
                    "CCODI_AUTO": "00000011",
                    "CON_EMITIDOS": "1.099",
                    "CON_VALIDOS": "2.899",
                    "NLISTA": 4,
                    "TOTAL_VOTOS1": "0",
                    "TOTAL_VOTOS10": "0",
                    "TOTAL_VOTOS11": "0",
                    "TOTAL_VOTOS12": "0",
                    "TOTAL_VOTOS13": "0",
                    "TOTAL_VOTOS14": "0",
                    "TOTAL_VOTOS15": "0",
                    "TOTAL_VOTOS16": "0",
                    "TOTAL_VOTOS2": "0",
                    "TOTAL_VOTOS3": "1",
                    "TOTAL_VOTOS4": "0",
                    "TOTAL_VOTOS5": "0",
                    "TOTAL_VOTOS6": "0",
                    "TOTAL_VOTOS7": "0",
                    "TOTAL_VOTOS8": "0",
                    "TOTAL_VOTOS9": "0",
                    "congresal": "2"
                },
                {
                    "AUTORIDAD": " ",
                    "CCODI_AUTO": "00000000",
                    "CON_EMITIDOS": "0.000",
                    "CON_VALIDOS": "0.000",
                    "NLISTA": 5,
                    "TOTAL_VOTOS1": "0",
                    "TOTAL_VOTOS10": "0",
                    "TOTAL_VOTOS11": "0",
                    "TOTAL_VOTOS12": "0",
                    "TOTAL_VOTOS13": "0",
                    "TOTAL_VOTOS14": "0",
                    "TOTAL_VOTOS15": "0",
                    "TOTAL_VOTOS16": "0",
                    "TOTAL_VOTOS2": "0",
                    "TOTAL_VOTOS3": "0",
                    "TOTAL_VOTOS4": "0",
                    "TOTAL_VOTOS5": "0",
                    "TOTAL_VOTOS6": "0",
                    "TOTAL_VOTOS7": "0",
                    "TOTAL_VOTOS8": "0",
                    "TOTAL_VOTOS9": "0",
                    "congresal": "0"
                },
                {
                    "AUTORIDAD": " ",
                    "CCODI_AUTO": "00000000",
                    "CON_EMITIDOS": "0.000",
                    "CON_VALIDOS": "0.000",
                    "NLISTA": 6,
                    "TOTAL_VOTOS1": "0",
                    "TOTAL_VOTOS10": "0",
                    "TOTAL_VOTOS11": "0",
                    "TOTAL_VOTOS12": "0",
                    "TOTAL_VOTOS13": "0",
                    "TOTAL_VOTOS14": "0",
                    "TOTAL_VOTOS15": "0",
                    "TOTAL_VOTOS16": "0",
                    "TOTAL_VOTOS2": "0",
                    "TOTAL_VOTOS3": "0",
                    "TOTAL_VOTOS4": "0",
                    "TOTAL_VOTOS5": "0",
                    "TOTAL_VOTOS6": "0",
                    "TOTAL_VOTOS7": "0",
                    "TOTAL_VOTOS8": "0",
                    "TOTAL_VOTOS9": "0",
                    "congresal": "0"
                },
                {
                    "AUTORIDAD": "ACCION POPULAR",
                    "CCODI_AUTO": "00000001",
                    "CON_EMITIDOS": "7.692",
                    "CON_VALIDOS": "20.290",
                    "NLISTA": 7,
                    "TOTAL_VOTOS1": "5",
                    "TOTAL_VOTOS10": "0",
                    "TOTAL_VOTOS11": "0",
                    "TOTAL_VOTOS12": "0",
                    "TOTAL_VOTOS13": "0",
                    "TOTAL_VOTOS14": "0",
                    "TOTAL_VOTOS15": "0",
                    "TOTAL_VOTOS16": "0",
                    "TOTAL_VOTOS2": "0",
                    "TOTAL_VOTOS3": "0",
                    "TOTAL_VOTOS4": "1",
                    "TOTAL_VOTOS5": "0",
                    "TOTAL_VOTOS6": "0",
                    "TOTAL_VOTOS7": "0",
                    "TOTAL_VOTOS8": "0",
                    "TOTAL_VOTOS9": "0",
                    "congresal": "14"
                },
                {
                    "AUTORIDAD": "AVANZA PAIS - PARTIDO DE INTEGRACION SOCIAL",
                    "CCODI_AUTO": "00000003",
                    "CON_EMITIDOS": "2.198",
                    "CON_VALIDOS": "5.797",
                    "NLISTA": 8,
                    "TOTAL_VOTOS1": "0",
                    "TOTAL_VOTOS10": "0",
                    "TOTAL_VOTOS11": "0",
                    "TOTAL_VOTOS12": "0",
                    "TOTAL_VOTOS13": "0",
                    "TOTAL_VOTOS14": "0",
                    "TOTAL_VOTOS15": "0",
                    "TOTAL_VOTOS16": "0",
                    "TOTAL_VOTOS2": "0",
                    "TOTAL_VOTOS3": "0",
                    "TOTAL_VOTOS4": "0",
                    "TOTAL_VOTOS5": "0",
                    "TOTAL_VOTOS6": "0",
                    "TOTAL_VOTOS7": "0",
                    "TOTAL_VOTOS8": "0",
                    "TOTAL_VOTOS9": "0",
                    "congresal": "4"
                },
                {
                    "AUTORIDAD": "PODEMOS PERU",
                    "CCODI_AUTO": "00000018",
                    "CON_EMITIDOS": "1.099",
                    "CON_VALIDOS": "2.899",
                    "NLISTA": 9,
                    "TOTAL_VOTOS1": "0",
                    "TOTAL_VOTOS10": "0",
                    "TOTAL_VOTOS11": "0",
                    "TOTAL_VOTOS12": "0",
                    "TOTAL_VOTOS13": "0",
                    "TOTAL_VOTOS14": "0",
                    "TOTAL_VOTOS15": "0",
                    "TOTAL_VOTOS16": "0",
                    "TOTAL_VOTOS2": "1",
                    "TOTAL_VOTOS3": "0",
                    "TOTAL_VOTOS4": "1",
                    "TOTAL_VOTOS5": "0",
                    "TOTAL_VOTOS6": "0",
                    "TOTAL_VOTOS7": "0",
                    "TOTAL_VOTOS8": "0",
                    "TOTAL_VOTOS9": "0",
                    "congresal": "2"
                },
                {
                    "AUTORIDAD": "JUNTOS POR EL PERU",
                    "CCODI_AUTO": "00000008",
                    "CON_EMITIDOS": "1.648",
                    "CON_VALIDOS": "4.348",
                    "NLISTA": 10,
                    "TOTAL_VOTOS1": "2",
                    "TOTAL_VOTOS10": "0",
                    "TOTAL_VOTOS11": "0",
                    "TOTAL_VOTOS12": "0",
                    "TOTAL_VOTOS13": "0",
                    "TOTAL_VOTOS14": "0",
                    "TOTAL_VOTOS15": "0",
                    "TOTAL_VOTOS16": "0",
                    "TOTAL_VOTOS2": "2",
                    "TOTAL_VOTOS3": "0",
                    "TOTAL_VOTOS4": "1",
                    "TOTAL_VOTOS5": "0",
                    "TOTAL_VOTOS6": "0",
                    "TOTAL_VOTOS7": "0",
                    "TOTAL_VOTOS8": "0",
                    "TOTAL_VOTOS9": "0",
                    "congresal": "3"
                },
                {
                    "AUTORIDAD": "PARTIDO POPULAR CRISTIANO - PPC",
                    "CCODI_AUTO": "00000015",
                    "CON_EMITIDOS": "0.000",
                    "CON_VALIDOS": "0.000",
                    "NLISTA": 11,
                    "TOTAL_VOTOS1": "0",
                    "TOTAL_VOTOS10": "0",
                    "TOTAL_VOTOS11": "0",
                    "TOTAL_VOTOS12": "0",
                    "TOTAL_VOTOS13": "0",
                    "TOTAL_VOTOS14": "0",
                    "TOTAL_VOTOS15": "0",
                    "TOTAL_VOTOS16": "0",
                    "TOTAL_VOTOS2": "0",
                    "TOTAL_VOTOS3": "0",
                    "TOTAL_VOTOS4": "0",
                    "TOTAL_VOTOS5": "0",
                    "TOTAL_VOTOS6": "0",
                    "TOTAL_VOTOS7": "0",
                    "TOTAL_VOTOS8": "0",
                    "TOTAL_VOTOS9": "0",
                    "congresal": "0"
                },
                {
                    "AUTORIDAD": "FUERZA POPULAR",
                    "CCODI_AUTO": "00000007",
                    "CON_EMITIDOS": "1.648",
                    "CON_VALIDOS": "4.348",
                    "NLISTA": 12,
                    "TOTAL_VOTOS1": "1",
                    "TOTAL_VOTOS10": "0",
                    "TOTAL_VOTOS11": "0",
                    "TOTAL_VOTOS12": "0",
                    "TOTAL_VOTOS13": "0",
                    "TOTAL_VOTOS14": "0",
                    "TOTAL_VOTOS15": "0",
                    "TOTAL_VOTOS16": "0",
                    "TOTAL_VOTOS2": "1",
                    "TOTAL_VOTOS3": "0",
                    "TOTAL_VOTOS4": "1",
                    "TOTAL_VOTOS5": "0",
                    "TOTAL_VOTOS6": "0",
                    "TOTAL_VOTOS7": "0",
                    "TOTAL_VOTOS8": "0",
                    "TOTAL_VOTOS9": "0",
                    "congresal": "3"
                },
                {
                    "AUTORIDAD": " ",
                    "CCODI_AUTO": "00000000",
                    "CON_EMITIDOS": "0.000",
                    "CON_VALIDOS": "0.000",
                    "NLISTA": 14,
                    "TOTAL_VOTOS1": "0",
                    "TOTAL_VOTOS10": "0",
                    "TOTAL_VOTOS11": "0",
                    "TOTAL_VOTOS12": "0",
                    "TOTAL_VOTOS13": "0",
                    "TOTAL_VOTOS14": "0",
                    "TOTAL_VOTOS15": "0",
                    "TOTAL_VOTOS16": "0",
                    "TOTAL_VOTOS2": "0",
                    "TOTAL_VOTOS3": "0",
                    "TOTAL_VOTOS4": "0",
                    "TOTAL_VOTOS5": "0",
                    "TOTAL_VOTOS6": "0",
                    "TOTAL_VOTOS7": "0",
                    "TOTAL_VOTOS8": "0",
                    "TOTAL_VOTOS9": "0",
                    "congresal": "0"
                },
                {
                    "AUTORIDAD": "RENOVACION POPULAR",
                    "CCODI_AUTO": "00000020",
                    "CON_EMITIDOS": "4.396",
                    "CON_VALIDOS": "11.594",
                    "NLISTA": 15,
                    "TOTAL_VOTOS1": "1",
                    "TOTAL_VOTOS10": "0",
                    "TOTAL_VOTOS11": "0",
                    "TOTAL_VOTOS12": "0",
                    "TOTAL_VOTOS13": "0",
                    "TOTAL_VOTOS14": "0",
                    "TOTAL_VOTOS15": "0",
                    "TOTAL_VOTOS16": "0",
                    "TOTAL_VOTOS2": "0",
                    "TOTAL_VOTOS3": "0",
                    "TOTAL_VOTOS4": "2",
                    "TOTAL_VOTOS5": "0",
                    "TOTAL_VOTOS6": "0",
                    "TOTAL_VOTOS7": "0",
                    "TOTAL_VOTOS8": "0",
                    "TOTAL_VOTOS9": "0",
                    "congresal": "8"
                },
                {
                    "AUTORIDAD": "RENACIMIENTO UNIDO NACIONAL",
                    "CCODI_AUTO": "00000019",
                    "CON_EMITIDOS": "0.000",
                    "CON_VALIDOS": "0.000",
                    "NLISTA": 16,
                    "TOTAL_VOTOS1": "0",
                    "TOTAL_VOTOS10": "0",
                    "TOTAL_VOTOS11": "0",
                    "TOTAL_VOTOS12": "0",
                    "TOTAL_VOTOS13": "0",
                    "TOTAL_VOTOS14": "0",
                    "TOTAL_VOTOS15": "0",
                    "TOTAL_VOTOS16": "0",
                    "TOTAL_VOTOS2": "0",
                    "TOTAL_VOTOS3": "0",
                    "TOTAL_VOTOS4": "0",
                    "TOTAL_VOTOS5": "0",
                    "TOTAL_VOTOS6": "0",
                    "TOTAL_VOTOS7": "0",
                    "TOTAL_VOTOS8": "0",
                    "TOTAL_VOTOS9": "0",
                    "congresal": "0"
                },
                {
                    "AUTORIDAD": "PARTIDO DEMOCRATICO SOMOS PERU",
                    "CCODI_AUTO": "00000010",
                    "CON_EMITIDOS": "3.297",
                    "CON_VALIDOS": "8.696",
                    "NLISTA": 17,
                    "TOTAL_VOTOS1": "2",
                    "TOTAL_VOTOS10": "0",
                    "TOTAL_VOTOS11": "0",
                    "TOTAL_VOTOS12": "0",
                    "TOTAL_VOTOS13": "0",
                    "TOTAL_VOTOS14": "0",
                    "TOTAL_VOTOS15": "0",
                    "TOTAL_VOTOS16": "0",
                    "TOTAL_VOTOS2": "0",
                    "TOTAL_VOTOS3": "0",
                    "TOTAL_VOTOS4": "1",
                    "TOTAL_VOTOS5": "1",
                    "TOTAL_VOTOS6": "0",
                    "TOTAL_VOTOS7": "0",
                    "TOTAL_VOTOS8": "0",
                    "TOTAL_VOTOS9": "0",
                    "congresal": "6"
                },
                {
                    "AUTORIDAD": "PARTIDO POLITICO NACIONAL PERU LIBRE",
                    "CCODI_AUTO": "00000014",
                    "CON_EMITIDOS": "4.945",
                    "CON_VALIDOS": "13.043",
                    "NLISTA": 18,
                    "TOTAL_VOTOS1": "1",
                    "TOTAL_VOTOS10": "0",
                    "TOTAL_VOTOS11": "0",
                    "TOTAL_VOTOS12": "0",
                    "TOTAL_VOTOS13": "0",
                    "TOTAL_VOTOS14": "0",
                    "TOTAL_VOTOS15": "0",
                    "TOTAL_VOTOS16": "0",
                    "TOTAL_VOTOS2": "0",
                    "TOTAL_VOTOS3": "1",
                    "TOTAL_VOTOS4": "1",
                    "TOTAL_VOTOS5": "0",
                    "TOTAL_VOTOS6": "0",
                    "TOTAL_VOTOS7": "0",
                    "TOTAL_VOTOS8": "0",
                    "TOTAL_VOTOS9": "0",
                    "congresal": "9"
                },
                {
                    "AUTORIDAD": "DEMOCRACIA DIRECTA",
                    "CCODI_AUTO": "00000004",
                    "CON_EMITIDOS": "0.000",
                    "CON_VALIDOS": "0.000",
                    "NLISTA": 19,
                    "TOTAL_VOTOS1": "0",
                    "TOTAL_VOTOS10": "0",
                    "TOTAL_VOTOS11": "0",
                    "TOTAL_VOTOS12": "0",
                    "TOTAL_VOTOS13": "0",
                    "TOTAL_VOTOS14": "0",
                    "TOTAL_VOTOS15": "0",
                    "TOTAL_VOTOS16": "0",
                    "TOTAL_VOTOS2": "0",
                    "TOTAL_VOTOS3": "0",
                    "TOTAL_VOTOS4": "0",
                    "TOTAL_VOTOS5": "0",
                    "TOTAL_VOTOS6": "0",
                    "TOTAL_VOTOS7": "0",
                    "TOTAL_VOTOS8": "0",
                    "TOTAL_VOTOS9": "0",
                    "congresal": "0"
                },
                {
                    "AUTORIDAD": "ALIANZA PARA EL PROGRESO",
                    "CCODI_AUTO": "00000002",
                    "CON_EMITIDOS": "7.143",
                    "CON_VALIDOS": "18.841",
                    "NLISTA": 20,
                    "TOTAL_VOTOS1": "1",
                    "TOTAL_VOTOS10": "0",
                    "TOTAL_VOTOS11": "0",
                    "TOTAL_VOTOS12": "0",
                    "TOTAL_VOTOS13": "0",
                    "TOTAL_VOTOS14": "2",
                    "TOTAL_VOTOS15": "0",
                    "TOTAL_VOTOS16": "0",
                    "TOTAL_VOTOS2": "1",
                    "TOTAL_VOTOS3": "0",
                    "TOTAL_VOTOS4": "0",
                    "TOTAL_VOTOS5": "0",
                    "TOTAL_VOTOS6": "1",
                    "TOTAL_VOTOS7": "0",
                    "TOTAL_VOTOS8": "0",
                    "TOTAL_VOTOS9": "0",
                    "congresal": "13"
                },
                {
                    "AUTORIDAD": "TOTAL VOTOS VALIDOS",
                    "CCODI_AUTO": null,
                    "CON_EMITIDOS": "37.912",
                    "CON_VALIDOS": "100.000",
                    "congresal": "69"
                },
                {
                    "AUTORIDAD": "VOTOS EN BLANCO",
                    "CCODI_AUTO": "80",
                    "CON_EMITIDOS": "43.956",
                    "CON_VALIDOS": null,
                    "congresal": "80"
                },
                {
                    "AUTORIDAD": "VOTOS NULOS",
                    "CCODI_AUTO": "80",
                    "CON_EMITIDOS": "18.132",
                    "CON_VALIDOS": null,
                    "congresal": "33"
                },
                {
                    "AUTORIDAD": "VOTOS IMPUGNADOS",
                    "CCODI_AUTO": "80",
                    "CON_EMITIDOS": "0.000",
                    "CON_VALIDOS": null,
                    "congresal": "0"
                },
                {
                    "AUTORIDAD": "TOTAL VOTOS EMITIDOS",
                    "CCODI_AUTO": null,
                    "CON_EMITIDOS": "100.000",
                    "CON_VALIDOS": "37.912",
                    "congresal": "182"
                }
            ]
        },
        "generalPre": {
            "presidencial": {
                "CCENT_COMPU": "C44057",
                "CCODI_UBIGEO": "130201",
                "CCOPIA_ACTA": "10A",
                "DEPARTAMENTO": "LAMBAYEQUE",
                "DISTRITO": "FERRE\u00d1AFE",
                "NNUME_HABILM": 300,
                "N_CANDIDATOS": 0,
                "OBSERVACION": "CONTABILIZADAS NORMALES",
                "OBSERVACION_TXT": "ACTA ELECTORAL NORMAL",
                "PROVINCIA": "FERRE\u00d1AFE",
                "TDIRE_LOCAL": "CALLE TRES MARIAS 830",
                "TNOMB_LOCAL": "IE 10059 JUAN GALO MU\u00d1OZ PALACIOS",
                "TOT_CIUDADANOS_VOTARON": 182
            },
            "resoluciones": [],
            "votos": [
                {
                    "AUTORIDAD": null,
                    "CCODI_AUTO": "00000000",
                    "CON_EMITIDOS": "0.000",
                    "CON_VALIDOS": "0.000",
                    "NLISTA": "1",
                    "congresal": "0"
                },
                {
                    "AUTORIDAD": "PARTIDO NACIONALISTA PERUANO",
                    "CCODI_AUTO": "00000012",
                    "CON_EMITIDOS": "0.549",
                    "CON_VALIDOS": "0.709",
                    "NLISTA": "2",
                    "congresal": "1"
                },
                {
                    "AUTORIDAD": "EL FRENTE AMPLIO POR JUSTICIA, VIDA Y LIBERTAD",
                    "CCODI_AUTO": "00000005",
                    "CON_EMITIDOS": "0.000",
                    "CON_VALIDOS": "0.000",
                    "NLISTA": "3",
                    "congresal": "0"
                },
                {
                    "AUTORIDAD": "PARTIDO MORADO",
                    "CCODI_AUTO": "00000011",
                    "CON_EMITIDOS": "1.648",
                    "CON_VALIDOS": "2.128",
                    "NLISTA": "4",
                    "congresal": "3"
                },
                {
                    "AUTORIDAD": "PERU PATRIA SEGURA",
                    "CCODI_AUTO": "00000017",
                    "CON_EMITIDOS": "1.648",
                    "CON_VALIDOS": "2.128",
                    "NLISTA": "5",
                    "congresal": "3"
                },
                {
                    "AUTORIDAD": "VICTORIA NACIONAL",
                    "CCODI_AUTO": "00000022",
                    "CON_EMITIDOS": "4.396",
                    "CON_VALIDOS": "5.674",
                    "NLISTA": "6",
                    "congresal": "8"
                },
                {
                    "AUTORIDAD": "ACCION POPULAR",
                    "CCODI_AUTO": "00000001",
                    "CON_EMITIDOS": "14.286",
                    "CON_VALIDOS": "18.440",
                    "NLISTA": "7",
                    "congresal": "26"
                },
                {
                    "AUTORIDAD": "AVANZA PAIS - PARTIDO DE INTEGRACION SOCIAL",
                    "CCODI_AUTO": "00000003",
                    "CON_EMITIDOS": "4.396",
                    "CON_VALIDOS": "5.674",
                    "NLISTA": "8",
                    "congresal": "8"
                },
                {
                    "AUTORIDAD": "PODEMOS PERU",
                    "CCODI_AUTO": "00000018",
                    "CON_EMITIDOS": "2.747",
                    "CON_VALIDOS": "3.546",
                    "NLISTA": "9",
                    "congresal": "5"
                },
                {
                    "AUTORIDAD": "JUNTOS POR EL PERU",
                    "CCODI_AUTO": "00000008",
                    "CON_EMITIDOS": "4.396",
                    "CON_VALIDOS": "5.674",
                    "NLISTA": "10",
                    "congresal": "8"
                },
                {
                    "AUTORIDAD": "PARTIDO POPULAR CRISTIANO - PPC",
                    "CCODI_AUTO": "00000015",
                    "CON_EMITIDOS": "0.000",
                    "CON_VALIDOS": "0.000",
                    "NLISTA": "11",
                    "congresal": "0"
                },
                {
                    "AUTORIDAD": "FUERZA POPULAR",
                    "CCODI_AUTO": "00000007",
                    "CON_EMITIDOS": "9.341",
                    "CON_VALIDOS": "12.057",
                    "NLISTA": "12",
                    "congresal": "17"
                },
                {
                    "AUTORIDAD": "UNION POR EL PERU",
                    "CCODI_AUTO": "00000021",
                    "CON_EMITIDOS": "0.000",
                    "CON_VALIDOS": "0.000",
                    "NLISTA": "14",
                    "congresal": "0"
                },
                {
                    "AUTORIDAD": "RENOVACION POPULAR",
                    "CCODI_AUTO": "00000020",
                    "CON_EMITIDOS": "13.187",
                    "CON_VALIDOS": "17.021",
                    "NLISTA": "15",
                    "congresal": "24"
                },
                {
                    "AUTORIDAD": "RENACIMIENTO UNIDO NACIONAL",
                    "CCODI_AUTO": "00000019",
                    "CON_EMITIDOS": "0.000",
                    "CON_VALIDOS": "0.000",
                    "NLISTA": "16",
                    "congresal": "0"
                },
                {
                    "AUTORIDAD": "PARTIDO DEMOCRATICO SOMOS PERU",
                    "CCODI_AUTO": "00000010",
                    "CON_EMITIDOS": "2.198",
                    "CON_VALIDOS": "2.837",
                    "NLISTA": "17",
                    "congresal": "4"
                },
                {
                    "AUTORIDAD": "PARTIDO POLITICO NACIONAL PERU LIBRE",
                    "CCODI_AUTO": "00000014",
                    "CON_EMITIDOS": "8.242",
                    "CON_VALIDOS": "10.638",
                    "NLISTA": "18",
                    "congresal": "15"
                },
                {
                    "AUTORIDAD": "DEMOCRACIA DIRECTA",
                    "CCODI_AUTO": "00000004",
                    "CON_EMITIDOS": "0.000",
                    "CON_VALIDOS": "0.000",
                    "NLISTA": "19",
                    "congresal": "0"
                },
                {
                    "AUTORIDAD": "ALIANZA PARA EL PROGRESO",
                    "CCODI_AUTO": "00000002",
                    "CON_EMITIDOS": "10.440",
                    "CON_VALIDOS": "13.475",
                    "NLISTA": "20",
                    "congresal": "19"
                },
                {
                    "AUTORIDAD": "TOTAL VOTOS VALIDOS",
                    "CCODI_AUTO": null,
                    "CON_EMITIDOS": "77.473",
                    "CON_VALIDOS": "100.000",
                    "congresal": "141"
                },
                {
                    "AUTORIDAD": "VOTOS EN BLANCO",
                    "CCODI_AUTO": "80",
                    "CON_EMITIDOS": "18.132",
                    "CON_VALIDOS": null,
                    "congresal": "33"
                },
                {
                    "AUTORIDAD": "VOTOS NULOS",
                    "CCODI_AUTO": "80",
                    "CON_EMITIDOS": "4.396",
                    "CON_VALIDOS": null,
                    "congresal": "8"
                },
                {
                    "AUTORIDAD": "VOTOS IMPUGNADOS",
                    "CCODI_AUTO": "80",
                    "CON_EMITIDOS": "0.000",
                    "CON_VALIDOS": null,
                    "congresal": "0"
                },
                {
                    "AUTORIDAD": "TOTAL VOTOS EMITIDOS",
                    "CCODI_AUTO": null,
                    "CON_EMITIDOS": "100.000",
                    "CON_VALIDOS": "77.473",
                    "congresal": "182"
                }
            ]
        },
        "realImages": "1"
    }
}